zero_harm_ai_detectors/__init__.py
zero_harm_ai_detectors/_version.py
zero_harm_ai_detectors/ai_detectors.py
zero_harm_ai_detectors/detectors.py
zero_harm_ai_detectors/harmful_detectors.py
zero_harm_ai_detectors-0.2.3.dist-info/licenses/LICENSE
zero_harm_ai_detectors-0.2.3.dist-info/METADATA
zero_harm_ai_detectors-0.2.3.dist-info/WHEEL
zero_harm_ai_detectors-0.2.3.dist-info/top_level.txt
zero_harm_ai_detectors-0.2.3.dist-info/RECORD
