Metadata-Version: 2.4
Name: zero_harm_ai_detectors
Version: 0.2.3
Summary: AI-powered privacy and harmful content detection library
Author-email: Zero Harm AI LLC <info@zeroharmai.com>
License: MIT
Project-URL: Homepage, https://github.com/Zero-Harm-AI-LLC/zero-harm-ai-detectors
Project-URL: Repository, https://github.com/Zero-Harm-AI-LLC/zero-harm-ai-detectors
Project-URL: Issues, https://github.com/Zero-Harm-AI-LLC/zero-harm-ai-detectors/issues
Classifier: Development Status :: 4 - Beta
Classifier: Intended Audience :: Developers
Classifier: Programming Language :: Python :: 3
Classifier: Programming Language :: Python :: 3.8
Classifier: Programming Language :: Python :: 3.9
Classifier: Programming Language :: Python :: 3.10
Classifier: Programming Language :: Python :: 3.11
Classifier: Programming Language :: Python :: 3.12
Classifier: Topic :: Security
Classifier: Topic :: Text Processing :: Linguistic
Requires-Python: >=3.8
License-File: LICENSE
Requires-Dist: regex>=2022.1.18
Requires-Dist: numpy>=1.21.0
Provides-Extra: ai
Requires-Dist: transformers>=4.30.0; extra == "ai"
Requires-Dist: torch>=2.0.0; extra == "ai"
Requires-Dist: sentencepiece>=0.1.99; extra == "ai"
Requires-Dist: protobuf>=3.20.0; extra == "ai"
Provides-Extra: dev
Requires-Dist: pytest>=7.4.0; extra == "dev"
Requires-Dist: pytest-cov>=4.1.0; extra == "dev"
Requires-Dist: black>=23.0.0; extra == "dev"
Requires-Dist: flake8>=6.0.0; extra == "dev"
Provides-Extra: all
Requires-Dist: transformers>=4.30.0; extra == "all"
Requires-Dist: torch>=2.0.0; extra == "all"
Requires-Dist: sentencepiece>=0.1.99; extra == "all"
Requires-Dist: protobuf>=3.20.0; extra == "all"
Requires-Dist: pytest>=7.4.0; extra == "all"
Requires-Dist: pytest-cov>=4.1.0; extra == "all"
Requires-Dist: black>=23.0.0; extra == "all"
Requires-Dist: flake8>=6.0.0; extra == "all"
Dynamic: license-file
